crag/__init__.py
crag/data/test.gen.gz
crag/data/test.out
crag/data/test.sample
crag-1.0.4.data/scripts/crag.py
crag-1.0.4.dist-info/METADATA
crag-1.0.4.dist-info/RECORD
crag-1.0.4.dist-info/WHEEL
crag-1.0.4.dist-info/top_level.txt
