Metadata-Version: 2.1
Name: crag
Version: 1.0.4
Summary: Competing Risk Analysis Genome-wide
Home-page: https://github.com/brfrancis/CompetingRisksAnalysisGW
Author: Ben Francis
Author-email: b.r.francis@liverpool.ac.uk
License: GPLv3
Keywords: competing risks survival analysis statistics data analysis
Platform: UNKNOWN
Classifier: Programming Language :: Python :: 2
Classifier: Programming Language :: Python :: 3
Classifier: License :: OSI Approved :: GNU General Public License v3 (GPLv3)
Classifier: Operating System :: OS Independent
Requires-Dist: pandas
Requires-Dist: argparse
Requires-Dist: numpy
Requires-Dist: lifelines
